homesweethome/homesweethome.py
homesweethome-0.5.0.dist-info/LICENSE
homesweethome-0.5.0.dist-info/METADATA
homesweethome-0.5.0.dist-info/WHEEL
homesweethome-0.5.0.dist-info/RECORD
