Metadata-Version: 2.3
Name: homesweethome
Version: 0.5.0
Summary: 
Author: Henryk Konsek
Author-email: hekonsek@gmail.com
Requires-Python: >=3.12
Classifier: Programming Language :: Python :: 3
Classifier: Programming Language :: Python :: 3.12
Classifier: Programming Language :: Python :: 3.13
Requires-Dist: dynaconf (>=3.2.6,<4.0.0)
Requires-Dist: pyyaml (>=6.0.2,<7.0.0)
